progression_qc/__init__.py
progression_qc/__main__.py
progression_qc/progression_qc.py
progression_qc/schemas/__init__.py
progression_qc/schemas/question_base.py
progression_qc/schemas/question_bd.py
progression_qc/schemas/question_prog.py
progression_qc/schemas/question_sys.py
progression_qc/schemas/question_vcs.py
progression_qc/schemas/rétroactions.py
progression_qc-0.3.0.dist-info/LICENSE
progression_qc-0.3.0.dist-info/METADATA
progression_qc-0.3.0.dist-info/WHEEL
progression_qc-0.3.0.dist-info/top_level.txt
progression_qc-0.3.0.dist-info/RECORD
