Metadata-Version: 2.1
Name: progression-qc
Version: 0.3.0
Summary: progression_qc est un compilateur/validateur pour la production de d'exercices pour Progression. progression_qc reçoit sur l'entrée standard ou en paramètre un fichier YAML contenant la description d'une question et reproduit sur la sortie standard le résultat traité et validé.
Home-page: https://git.dti.crosemont.quebec/progression/validateur
Author: Patrick Lafrance
Author-email: plafrance@crosemont.qc.ca
License: GPLv3+
Classifier: Programming Language :: Python :: 3
License-File: LICENSE
Requires-Dist: cerberus
Requires-Dist: pyyaml-include
Requires-Dist: werkzeug
